ROI2TEXT-1.2.dist-info/DESCRIPTION.rst
ROI2TEXT-1.2.dist-info/METADATA
ROI2TEXT-1.2.dist-info/RECORD
ROI2TEXT-1.2.dist-info/WHEEL
ROI2TEXT-1.2.dist-info/entry_points.txt
ROI2TEXT-1.2.dist-info/metadata.json
ROI2TEXT-1.2.dist-info/top_level.txt
roi2text/__init__.py
roi2text/roi2text.py
roi2text/tests/__init__.py
roi2text/tests/test_roi2text.py
